{"reportDate":"2026-05-12T12:56:09.774Z","weekLabel":"Week of May 4, 2026","weekStart":"2026-05-04","weekEnd":"2026-05-10","currentWeek":{"flightsExecuted":0,"grossRevenue":0,"pilotPay":0,"totalOperatingExpenses":-7773.62,"netPnL":7773.62,"margin":0,"typeBreakdown":{},"occurrenceRevenue":{"Recurring":0,"One-Off":0},"recurringPct":0,"oneOffPct":0,"xeroCosts":{"Professional Fees:Pilot":8165,"Project Related Costs":269.2,"Car/Truck Expense:Gas":-73.6,"Credit card processing fees":-808.09,"Dues and Subscriptions":-373.53,"Gifts":-121.92,"Insurance":-46,"Payment Fees - Textura":-6767.01,"Professional Fees:Payroll Service Fees":-200,"Wages - VA's":-7817.67}},"weeklyHistory":[],"monthlyData":[],"monthlyFlights":[],"_ts":1778590569779}